{
  "teams": {
    "Team 124": {
      "points": 135,
      "prs": 12,
      "contributors": [
        "PrinceDiyora",
        "kunj01",
        "RudraDudhat"
      ],
      "repos": [
        "Zaplink_frontend",
        "CareXpert_frontend",
        "Zaplink_backend",
        "CareXpert_backend"
      ]
    },
    "Team 173": {
      "points": 190,
      "prs": 14,
      "contributors": [
        "vasu-CE"
      ],
      "repos": [
        "Code_duel_frontend",
        "Code_duel_backend",
        "PDF_QA_Bot",
        "Zaplink_backend",
        "Zaplink_frontend"
      ]
    },
    "Team 152": {
      "points": 180,
      "prs": 15,
      "contributors": [
        "Krish3017",
        "Talaviya-Sarthak",
        "surejasmit"
      ],
      "repos": [
        "PDF_QA_Bot",
        "Code_duel_frontend",
        "Zaplink_backend",
        "CareXpert_backend",
        "CareXpert_frontend",
        "super-roast-bot"
      ]
    },
    "Team 177": {
      "points": 45,
      "prs": 3,
      "contributors": [
        "BhavyaManvar",
        "ybthummar"
      ],
      "repos": [
        "super-roast-bot",
        "CareXpert_frontend"
      ]
    },
    "Team 087": {
      "points": 25,
      "prs": 2,
      "contributors": [
        "Ansh-dhanani"
      ],
      "repos": [
        "super-roast-bot",
        "Zaplink_backend"
      ]
    },
    "Team 80": {
      "points": 25,
      "prs": 2,
      "contributors": [
        "Ommodi07"
      ],
      "repos": [
        "FMEA_SupplyChain"
      ]
    },
    "Team 120": {
      "points": 20,
      "prs": 1,
      "contributors": [
        "vraj826"
      ],
      "repos": [
        "PDF_QA_Bot"
      ]
    },
    "Team 149": {
      "points": 125,
      "prs": 10,
      "contributors": [
        "RutviShah2"
      ],
      "repos": [
        "Zaplink_frontend",
        "CareXpert_frontend",
        "FMEA_SupplyChain",
        "super-roast-bot",
        "PDF_QA_Bot"
      ]
    },
    "Team 052": {
      "points": 30,
      "prs": 6,
      "contributors": [
        "atul-upadhyay-7"
      ],
      "repos": [
        "Zaplink_frontend",
        "super-roast-bot",
        "CareXpert_frontend",
        "FMEA_SupplyChain"
      ]
    },
    "Team 123": {
      "points": 10,
      "prs": 2,
      "contributors": [
        "princedesai012",
        "rishi-sheladiya-26"
      ],
      "repos": [
        "Zaplink_backend",
        "Code_duel_frontend"
      ]
    },
    "Team 101": {
      "points": 15,
      "prs": 3,
      "contributors": [
        "ohmbhatia",
        "hetrakholiya11"
      ],
      "repos": [
        "CareXpert_frontend",
        "PDF_QA_Bot"
      ]
    },
    "Team 119": {
      "points": 20,
      "prs": 4,
      "contributors": [
        "HeerGhevariya",
        "smitgoyani123"
      ],
      "repos": [
        "CareXpert_frontend",
        "Code_duel_frontend"
      ]
    },
    "Team 125": {
      "points": 155,
      "prs": 10,
      "contributors": [
        "Diyap235",
        "Yashvi29-power"
      ],
      "repos": [
        "CareXpert_frontend",
        "Zaplink_frontend",
        "Code_duel_frontend"
      ]
    },
    "Team 109": {
      "points": 5,
      "prs": 1,
      "contributors": [
        "manthan2876"
      ],
      "repos": [
        "CareXpert_backend"
      ]
    },
    "Team 065": {
      "points": 65,
      "prs": 7,
      "contributors": [
        "Ashok089",
        "Shubhp0712",
        "samarthpatel2005"
      ],
      "repos": [
        "CareXpert_backend",
        "CareXpert_frontend",
        "Zaplink_backend",
        "Zaplink_frontend"
      ]
    },
    "Team 082": {
      "points": 65,
      "prs": 4,
      "contributors": [
        "dhruvpatel848"
      ],
      "repos": [
        "CareXpert_backend",
        "Zaplink_backend",
        "PDF_QA_Bot"
      ]
    },
    "Team 150": {
      "points": 70,
      "prs": 5,
      "contributors": [
        "Akshat14z",
        "dhrumil246"
      ],
      "repos": [
        "Code_duel_frontend",
        "PDF_QA_Bot",
        "CareXpert_backend"
      ]
    },
    "Team 167": {
      "points": 20,
      "prs": 1,
      "contributors": [
        "devvpin"
      ],
      "repos": [
        "Code_duel_frontend"
      ]
    },
    "Team 143": {
      "points": 50,
      "prs": 4,
      "contributors": [
        "HEETMEHTA18",
        "AryanPatelD",
        "KrishPatel1905"
      ],
      "repos": [
        "Zaplink_frontend",
        "Zaplink_backend",
        "FMEA_SupplyChain",
        "Code_duel_frontend"
      ]
    },
    "Team 153": {
      "points": 35,
      "prs": 4,
      "contributors": [
        "unnatii14",
        "Anshu-bhatt"
      ],
      "repos": [
        "PDF_QA_Bot",
        "CareXpert_backend"
      ]
    },
    "Team 135": {
      "points": 110,
      "prs": 7,
      "contributors": [
        "JainiSolanki",
        "HetviHR"
      ],
      "repos": [
        "PDF_QA_Bot",
        "Zaplink_frontend"
      ]
    },
    "Team 113": {
      "points": 30,
      "prs": 3,
      "contributors": [
        "7JankiPanchal",
        "sneha029"
      ],
      "repos": [
        "Code_duel_frontend",
        "CareXpert_frontend",
        "Zaplink_frontend"
      ]
    },
    "Team 163": {
      "points": 30,
      "prs": 3,
      "contributors": [
        "kevaljogani",
        "DaxGondaliya"
      ],
      "repos": [
        "PDF_QA_Bot",
        "CareXpert_backend"
      ]
    },
    "Team 132": {
      "points": 50,
      "prs": 4,
      "contributors": [
        "Mathakiya-Amal",
        "Aryanghadiya",
        "DeepMakwana-18"
      ],
      "repos": [
        "PDF_QA_Bot",
        "CareXpert_frontend",
        "super-roast-bot",
        "Zaplink_frontend"
      ]
    },
    "Team 114": {
      "points": 5,
      "prs": 1,
      "contributors": [
        "Preetsavaliya111"
      ],
      "repos": [
        "Code_duel_frontend"
      ]
    },
    "Team 072": {
      "points": 15,
      "prs": 3,
      "contributors": [
        "kushpatel2601"
      ],
      "repos": [
        "Zaplink_frontend",
        "PDF_QA_Bot",
        "super-roast-bot"
      ]
    },
    "Team 036": {
      "points": 35,
      "prs": 4,
      "contributors": [
        "Pratham3900",
        "pratham-25mca046"
      ],
      "repos": [
        "Zaplink_frontend",
        "CareXpert_backend",
        "Zaplink_backend",
        "PDF_QA_Bot"
      ]
    },
    "Team 137": {
      "points": 10,
      "prs": 2,
      "contributors": [
        "hindochahitarth"
      ],
      "repos": [
        "Zaplink_frontend"
      ]
    },
    "Team 161": {
      "points": 20,
      "prs": 1,
      "contributors": [
        "Jerry-145"
      ],
      "repos": [
        "CareXpert_frontend"
      ]
    },
    "Team 066": {
      "points": 65,
      "prs": 4,
      "contributors": [
        "chaitany851P"
      ],
      "repos": [
        "Code_duel_backend",
        "super-roast-bot",
        "Zaplink_backend"
      ]
    },
    "Team 168": {
      "points": 20,
      "prs": 1,
      "contributors": [
        "mayankpadmani"
      ],
      "repos": [
        "Code_duel_backend"
      ]
    },
    "Team 188": {
      "points": 15,
      "prs": 3,
      "contributors": [
        "24cs062"
      ],
      "repos": [
        "Zaplink_backend",
        "CareXpert_backend"
      ]
    },
    "Team 165": {
      "points": 45,
      "prs": 3,
      "contributors": [
        "satanismit"
      ],
      "repos": [
        "PDF_QA_Bot"
      ]
    },
    "Team 83": {
      "points": 45,
      "prs": 3,
      "contributors": [
        "DeepPatel4505",
        "NishitPDesai"
      ],
      "repos": [
        "Zaplink_backend",
        "CareXpert_backend",
        "PDF_QA_Bot"
      ]
    },
    "Team 146": {
      "points": 115,
      "prs": 8,
      "contributors": [
        "Dhruvi-kanabar30",
        "Ronit069",
        "Mahi1206",
        "Aryan-B-Parikh"
      ],
      "repos": [
        "Zaplink_backend",
        "CareXpert_backend",
        "CareXpert_frontend",
        "FMEA_SupplyChain"
      ]
    },
    "Team 170": {
      "points": 25,
      "prs": 2,
      "contributors": [
        "DakshSavani13"
      ],
      "repos": [
        "CareXpert_backend",
        "CareXpert_frontend"
      ]
    },
    "Team 138": {
      "points": 10,
      "prs": 2,
      "contributors": [
        "Vaibhavi-1107",
        "Pushtikansara"
      ],
      "repos": [
        "CareXpert_frontend",
        "CareXpert_backend"
      ]
    },
    "Team 102": {
      "points": 45,
      "prs": 3,
      "contributors": [
        "PATELSHAIL7125",
        "MayankT1409",
        "Manthann07"
      ],
      "repos": [
        "CareXpert_frontend",
        "CareXpert_backend",
        "Zaplink_backend"
      ]
    },
    "Team 155": {
      "points": 35,
      "prs": 4,
      "contributors": [
        "KavyDave18",
        "harshitpambhar"
      ],
      "repos": [
        "super-roast-bot",
        "FMEA_SupplyChain"
      ]
    },
    "Team 171": {
      "points": 5,
      "prs": 1,
      "contributors": [
        "Aelees0807"
      ],
      "repos": [
        "Code_duel_frontend"
      ]
    },
    "Team 126": {
      "points": 25,
      "prs": 2,
      "contributors": [
        "PatelAaryan03",
        "Hetrajj07"
      ],
      "repos": [
        "CareXpert_backend"
      ]
    },
    "Team 131": {
      "points": 20,
      "prs": 1,
      "contributors": [
        "DarshitSorathiya"
      ],
      "repos": [
        "super-roast-bot"
      ]
    },
    "Team 186": {
      "points": 20,
      "prs": 1,
      "contributors": [
        "Raxnakum11"
      ],
      "repos": [
        "super-roast-bot"
      ]
    },
    "Team 144": {
      "points": 5,
      "prs": 1,
      "contributors": [
        "renanaik"
      ],
      "repos": [
        "FMEA_SupplyChain"
      ]
    },
    "Team 147": {
      "points": 5,
      "prs": 1,
      "contributors": [
        "Deepbhalani1277"
      ],
      "repos": [
        "FMEA_SupplyChain"
      ]
    },
    "Team 107": {
      "points": 25,
      "prs": 2,
      "contributors": [
        "Sp2736"
      ],
      "repos": [
        "CareXpert_frontend",
        "Zaplink_frontend"
      ]
    },
    "Team 187": {
      "points": 40,
      "prs": 2,
      "contributors": [
        "Yashgohel018"
      ],
      "repos": [
        "CareXpert_frontend",
        "Zaplink_frontend"
      ]
    }
  },
  "contributors": {
    "PrinceDiyora": {
      "points": 20,
      "prs": 4,
      "team": "Team 124",
      "repos": [
        "Zaplink_frontend",
        "CareXpert_frontend"
      ]
    },
    "vasu-CE": {
      "points": 190,
      "prs": 14,
      "team": "Team 173",
      "repos": [
        "Code_duel_frontend",
        "Code_duel_backend",
        "PDF_QA_Bot",
        "Zaplink_backend",
        "Zaplink_frontend"
      ]
    },
    "Krish3017": {
      "points": 90,
      "prs": 9,
      "team": "Team 152",
      "repos": [
        "PDF_QA_Bot",
        "Code_duel_frontend",
        "CareXpert_backend",
        "Zaplink_backend",
        "CareXpert_frontend"
      ]
    },
    "BhavyaManvar": {
      "points": 40,
      "prs": 2,
      "team": "Team 177",
      "repos": [
        "super-roast-bot",
        "CareXpert_frontend"
      ]
    },
    "Ansh-dhanani": {
      "points": 25,
      "prs": 2,
      "team": "Team 087",
      "repos": [
        "super-roast-bot",
        "Zaplink_backend"
      ]
    },
    "Ommodi07": {
      "points": 25,
      "prs": 2,
      "team": "Team 80",
      "repos": [
        "FMEA_SupplyChain"
      ]
    },
    "vraj826": {
      "points": 20,
      "prs": 1,
      "team": "Team 120",
      "repos": [
        "PDF_QA_Bot"
      ]
    },
    "RutviShah2": {
      "points": 125,
      "prs": 10,
      "team": "Team 149",
      "repos": [
        "Zaplink_frontend",
        "CareXpert_frontend",
        "FMEA_SupplyChain",
        "super-roast-bot",
        "PDF_QA_Bot"
      ]
    },
    "atul-upadhyay-7": {
      "points": 30,
      "prs": 6,
      "team": "Team 052",
      "repos": [
        "Zaplink_frontend",
        "super-roast-bot",
        "CareXpert_frontend",
        "FMEA_SupplyChain"
      ]
    },
    "princedesai012": {
      "points": 5,
      "prs": 1,
      "team": "Team 123",
      "repos": [
        "Zaplink_backend"
      ]
    },
    "ohmbhatia": {
      "points": 10,
      "prs": 2,
      "team": "Team 101",
      "repos": [
        "CareXpert_frontend"
      ]
    },
    "HeerGhevariya": {
      "points": 10,
      "prs": 2,
      "team": "Team 119",
      "repos": [
        "CareXpert_frontend"
      ]
    },
    "Diyap235": {
      "points": 115,
      "prs": 8,
      "team": "Team 125",
      "repos": [
        "CareXpert_frontend",
        "Code_duel_frontend"
      ]
    },
    "manthan2876": {
      "points": 5,
      "prs": 1,
      "team": "Team 109",
      "repos": [
        "CareXpert_backend"
      ]
    },
    "Ashok089": {
      "points": 45,
      "prs": 3,
      "team": "Team 065",
      "repos": [
        "CareXpert_backend",
        "CareXpert_frontend"
      ]
    },
    "dhruvpatel848": {
      "points": 65,
      "prs": 4,
      "team": "Team 082",
      "repos": [
        "CareXpert_backend",
        "PDF_QA_Bot",
        "Zaplink_backend"
      ]
    },
    "Akshat14z": {
      "points": 45,
      "prs": 3,
      "team": "Team 150",
      "repos": [
        "Code_duel_frontend",
        "PDF_QA_Bot"
      ]
    },
    "devvpin": {
      "points": 20,
      "prs": 1,
      "team": "Team 167",
      "repos": [
        "Code_duel_frontend"
      ]
    },
    "kunj01": {
      "points": 45,
      "prs": 3,
      "team": "Team 124",
      "repos": [
        "Zaplink_frontend",
        "CareXpert_frontend"
      ]
    },
    "HEETMEHTA18": {
      "points": 40,
      "prs": 2,
      "team": "Team 143",
      "repos": [
        "Zaplink_frontend",
        "FMEA_SupplyChain"
      ]
    },
    "unnatii14": {
      "points": 30,
      "prs": 3,
      "team": "Team 153",
      "repos": [
        "PDF_QA_Bot",
        "CareXpert_backend"
      ]
    },
    "JainiSolanki": {
      "points": 50,
      "prs": 4,
      "team": "Team 135",
      "repos": [
        "PDF_QA_Bot",
        "Zaplink_frontend"
      ]
    },
    "HetviHR": {
      "points": 60,
      "prs": 3,
      "team": "Team 135",
      "repos": [
        "PDF_QA_Bot"
      ]
    },
    "rishi-sheladiya-26": {
      "points": 5,
      "prs": 1,
      "team": "Team 123",
      "repos": [
        "Code_duel_frontend"
      ]
    },
    "7JankiPanchal": {
      "points": 25,
      "prs": 2,
      "team": "Team 113",
      "repos": [
        "Code_duel_frontend",
        "CareXpert_frontend"
      ]
    },
    "kevaljogani": {
      "points": 25,
      "prs": 2,
      "team": "Team 163",
      "repos": [
        "PDF_QA_Bot"
      ]
    },
    "Mathakiya-Amal": {
      "points": 10,
      "prs": 2,
      "team": "Team 132",
      "repos": [
        "PDF_QA_Bot",
        "CareXpert_frontend"
      ]
    },
    "smitgoyani123": {
      "points": 10,
      "prs": 2,
      "team": "Team 119",
      "repos": [
        "Code_duel_frontend",
        "CareXpert_frontend"
      ]
    },
    "Preetsavaliya111": {
      "points": 5,
      "prs": 1,
      "team": "Team 114",
      "repos": [
        "Code_duel_frontend"
      ]
    },
    "kushpatel2601": {
      "points": 15,
      "prs": 3,
      "team": "Team 072",
      "repos": [
        "Zaplink_frontend",
        "PDF_QA_Bot",
        "super-roast-bot"
      ]
    },
    "Yashvi29-power": {
      "points": 40,
      "prs": 2,
      "team": "Team 125",
      "repos": [
        "Zaplink_frontend"
      ]
    },
    "Pratham3900": {
      "points": 30,
      "prs": 3,
      "team": "Team 036",
      "repos": [
        "Zaplink_frontend",
        "Zaplink_backend",
        "PDF_QA_Bot"
      ]
    },
    "hindochahitarth": {
      "points": 10,
      "prs": 2,
      "team": "Team 137",
      "repos": [
        "Zaplink_frontend"
      ]
    },
    "ybthummar": {
      "points": 5,
      "prs": 1,
      "team": "Team 177",
      "repos": [
        "CareXpert_frontend"
      ]
    },
    "Jerry-145": {
      "points": 20,
      "prs": 1,
      "team": "Team 161",
      "repos": [
        "CareXpert_frontend"
      ]
    },
    "chaitany851P": {
      "points": 65,
      "prs": 4,
      "team": "Team 066",
      "repos": [
        "Code_duel_backend",
        "super-roast-bot",
        "Zaplink_backend"
      ]
    },
    "mayankpadmani": {
      "points": 20,
      "prs": 1,
      "team": "Team 168",
      "repos": [
        "Code_duel_backend"
      ]
    },
    "24cs062": {
      "points": 15,
      "prs": 3,
      "team": "Team 188",
      "repos": [
        "Zaplink_backend",
        "CareXpert_backend"
      ]
    },
    "satanismit": {
      "points": 45,
      "prs": 3,
      "team": "Team 165",
      "repos": [
        "PDF_QA_Bot"
      ]
    },
    "hetrakholiya11": {
      "points": 5,
      "prs": 1,
      "team": "Team 101",
      "repos": [
        "PDF_QA_Bot"
      ]
    },
    "RudraDudhat": {
      "points": 70,
      "prs": 5,
      "team": "Team 124",
      "repos": [
        "Zaplink_backend",
        "Zaplink_frontend",
        "CareXpert_backend"
      ]
    },
    "Talaviya-Sarthak": {
      "points": 50,
      "prs": 4,
      "team": "Team 152",
      "repos": [
        "Zaplink_backend",
        "CareXpert_backend"
      ]
    },
    "DeepPatel4505": {
      "points": 25,
      "prs": 2,
      "team": "Team 83",
      "repos": [
        "Zaplink_backend",
        "PDF_QA_Bot"
      ]
    },
    "AryanPatelD": {
      "points": 5,
      "prs": 1,
      "team": "Team 143",
      "repos": [
        "Zaplink_backend"
      ]
    },
    "Dhruvi-kanabar30": {
      "points": 10,
      "prs": 2,
      "team": "Team 146",
      "repos": [
        "Zaplink_backend"
      ]
    },
    "dhrumil246": {
      "points": 25,
      "prs": 2,
      "team": "Team 150",
      "repos": [
        "CareXpert_backend"
      ]
    },
    "DakshSavani13": {
      "points": 25,
      "prs": 2,
      "team": "Team 170",
      "repos": [
        "CareXpert_backend",
        "CareXpert_frontend"
      ]
    },
    "DaxGondaliya": {
      "points": 5,
      "prs": 1,
      "team": "Team 163",
      "repos": [
        "CareXpert_backend"
      ]
    },
    "NishitPDesai": {
      "points": 20,
      "prs": 1,
      "team": "Team 83",
      "repos": [
        "CareXpert_backend"
      ]
    },
    "Vaibhavi-1107": {
      "points": 5,
      "prs": 1,
      "team": "Team 138",
      "repos": [
        "CareXpert_frontend"
      ]
    },
    "Ronit069": {
      "points": 20,
      "prs": 1,
      "team": "Team 146",
      "repos": [
        "CareXpert_backend"
      ]
    },
    "PATELSHAIL7125": {
      "points": 20,
      "prs": 1,
      "team": "Team 102",
      "repos": [
        "CareXpert_frontend"
      ]
    },
    "KavyDave18": {
      "points": 5,
      "prs": 1,
      "team": "Team 155",
      "repos": [
        "super-roast-bot"
      ]
    },
    "Aelees0807": {
      "points": 5,
      "prs": 1,
      "team": "Team 171",
      "repos": [
        "Code_duel_frontend"
      ]
    },
    "PatelAaryan03": {
      "points": 20,
      "prs": 1,
      "team": "Team 126",
      "repos": [
        "CareXpert_backend"
      ]
    },
    "pratham-25mca046": {
      "points": 5,
      "prs": 1,
      "team": "Team 036",
      "repos": [
        "CareXpert_backend"
      ]
    },
    "MayankT1409": {
      "points": 5,
      "prs": 1,
      "team": "Team 102",
      "repos": [
        "CareXpert_backend"
      ]
    },
    "Mahi1206": {
      "points": 25,
      "prs": 2,
      "team": "Team 146",
      "repos": [
        "CareXpert_frontend",
        "FMEA_SupplyChain"
      ]
    },
    "DarshitSorathiya": {
      "points": 20,
      "prs": 1,
      "team": "Team 131",
      "repos": [
        "super-roast-bot"
      ]
    },
    "Aryanghadiya": {
      "points": 20,
      "prs": 1,
      "team": "Team 132",
      "repos": [
        "super-roast-bot"
      ]
    },
    "Raxnakum11": {
      "points": 20,
      "prs": 1,
      "team": "Team 186",
      "repos": [
        "super-roast-bot"
      ]
    },
    "harshitpambhar": {
      "points": 30,
      "prs": 3,
      "team": "Team 155",
      "repos": [
        "super-roast-bot",
        "FMEA_SupplyChain"
      ]
    },
    "renanaik": {
      "points": 5,
      "prs": 1,
      "team": "Team 144",
      "repos": [
        "FMEA_SupplyChain"
      ]
    },
    "Aryan-B-Parikh": {
      "points": 60,
      "prs": 3,
      "team": "Team 146",
      "repos": [
        "FMEA_SupplyChain",
        "CareXpert_frontend",
        "CareXpert_backend"
      ]
    },
    "Manthann07": {
      "points": 20,
      "prs": 1,
      "team": "Team 102",
      "repos": [
        "Zaplink_backend"
      ]
    },
    "Deepbhalani1277": {
      "points": 5,
      "prs": 1,
      "team": "Team 147",
      "repos": [
        "FMEA_SupplyChain"
      ]
    },
    "Shubhp0712": {
      "points": 5,
      "prs": 1,
      "team": "Team 065",
      "repos": [
        "Zaplink_backend"
      ]
    },
    "Sp2736": {
      "points": 25,
      "prs": 2,
      "team": "Team 107",
      "repos": [
        "CareXpert_frontend",
        "Zaplink_frontend"
      ]
    },
    "Yashgohel018": {
      "points": 40,
      "prs": 2,
      "team": "Team 187",
      "repos": [
        "CareXpert_frontend",
        "Zaplink_frontend"
      ]
    },
    "surejasmit": {
      "points": 40,
      "prs": 2,
      "team": "Team 152",
      "repos": [
        "PDF_QA_Bot",
        "super-roast-bot"
      ]
    },
    "DeepMakwana-18": {
      "points": 20,
      "prs": 1,
      "team": "Team 132",
      "repos": [
        "Zaplink_frontend"
      ]
    },
    "sneha029": {
      "points": 5,
      "prs": 1,
      "team": "Team 113",
      "repos": [
        "Zaplink_frontend"
      ]
    },
    "samarthpatel2005": {
      "points": 15,
      "prs": 3,
      "team": "Team 065",
      "repos": [
        "Zaplink_frontend",
        "CareXpert_backend"
      ]
    },
    "Anshu-bhatt": {
      "points": 5,
      "prs": 1,
      "team": "Team 153",
      "repos": [
        "PDF_QA_Bot"
      ]
    },
    "Pushtikansara": {
      "points": 5,
      "prs": 1,
      "team": "Team 138",
      "repos": [
        "CareXpert_backend"
      ]
    },
    "Hetrajj07": {
      "points": 5,
      "prs": 1,
      "team": "Team 126",
      "repos": [
        "CareXpert_backend"
      ]
    },
    "KrishPatel1905": {
      "points": 5,
      "prs": 1,
      "team": "Team 143",
      "repos": [
        "Code_duel_frontend"
      ]
    }
  }
}